matrixhdl/__init__.py
matrixhdl/mh_export.py
matrixhdl/mh_hyperlink.py
matrixhdl/mh_import.py
matrixhdl/mh_ports.py
matrixhdl-0.1.10.dist-info/entry_points.txt
matrixhdl-0.1.10.dist-info/METADATA
matrixhdl-0.1.10.dist-info/WHEEL
matrixhdl-0.1.10.dist-info/RECORD
