Metadata-Version: 2.3
Name: matrixhdl
Version: 0.1.10
Summary: 
Author: lixinbingg
Author-email: lixinbingg@163.com
Requires-Python: >=3.10
Classifier: Programming Language :: Python :: 3
Classifier: Programming Language :: Python :: 3.10
Classifier: Programming Language :: Python :: 3.11
Classifier: Programming Language :: Python :: 3.12
Classifier: Programming Language :: Python :: 3.13
Requires-Dist: openpyxl
